<?xml version="1.0" encoding="utf-8"?>
<odoo>
    <menuitem name="TDA Glass Store" id="menu_item_tda_glass_store" web_icon="tda_glass_merchant,static/description/tda_logo.jpg" sequence="19" action="tda_product_action">
        <menuitem name="Products" id="menu_item_tda_product" action="tda_product_action" sequence="1"/>
        <menuitem name="Products Category" id="menu_item_tda_product_category" action="tda_product_category_action" sequence="2"/>
        <menuitem name="Advisory Request" id="menu_item_tda_advisory_request" action="tda_advisory_request_action" sequence="3"/>
        <menuitem name="Company info" id="menu_item_company_info_parent" sequence="4">
            <menuitem name="Company info" id="menu_item_company_info" action="tda_info_action" sequence="1"/>
            <menuitem name="Addresses" id="menu_item_address_info" action="tda_address_action" sequence="2"/>

            <menuitem name="Projects category" id="menu_item_tda_projects_category" action="tda_projects_category_action" sequence="3"/>
            <menuitem name="Projects" id="menu_item_tda_projects" action="tda_projects_action" sequence="4"/>
            <menuitem name="Feng Shui" id="menu_item_tda_feng_shui" action="tda_feng_shui_action" sequence="5"/>
        </menuitem>
    </menuitem>
</odoo>